{
  "id": 32,
  "age": 73.0,
  "sex": null,
  "n_advanced_organs": 0,
  "organs": [
    {
      "name": "liver",
      "display_name": "Liver",
      "biological_age": 48.597751458460195,
      "age_gap": -24.402248541539805,
      "status": "healthy",
      "advanced": false
    },
    {
      "name": "kidney",
      "display_name": "Kidney",
      "biological_age": 62.09215934839809,
      "age_gap": -10.907840651601909,
      "status": "healthy",
      "advanced": false
    },
    {
      "name": "cardio_metabolic",
      "display_name": "Cardio Metabolic",
      "biological_age": 57.8726218528307,
      "age_gap": -15.127378147169303,
      "status": "healthy",
      "advanced": false
    },
    {
      "name": "immune",
      "display_name": "Immune",
      "biological_age": 57.09529402761933,
      "age_gap": -15.904705972380668,
      "status": "healthy",
      "advanced": false
    },
    {
      "name": "hematologic",
      "display_name": "Hematologic",
      "biological_age": 62.78289226337234,
      "age_gap": -10.21710773662766,
      "status": "healthy",
      "advanced": false
    }
  ]
}